<!--
author Copyright (c) 2005 by BEE S.A. All Rights Reserved.
revision GestionRORAC@/Ror-001@
-->

<?xml version = "1.0" encoding = "ISO-8859-1" ?>
<!DOCTYPE service PUBLIC "-//BEE S.A.//DTD Transaction Definition//ES" "http://www.bee.cl/dtds/XMLService.dtd" >

<service name = "pedido_p001df8c2_a">

  <context>

    <boolean_false value="1" />

    <boolean_true value="0" />

    <general_exception_codigo value="ESPECIAL" />

    <have_multi_environment value="no" />

    <outputfield_attr value="no" />

    <req_num_param value="no" />

    <translator value="RORPPTPG" />

    <campo_indica_cantidad value="" />

    <status_throw_exception value="yes" />

    <joltpool_name value="wcorp.serv.gestionderorac.ServiciosGestionDeRORACBean" />

  </context>

  <input>

        <field
          java_name = "rut"
          type = "String"
          size = "8"
          middle_name = "rut"
        />

        <field
          java_name = "dv"
          type = "char"
          size = "1"
          middle_name = "digitoVerificador"
        />

        <field
          java_name = "fec_ini"
          type = "int"
          size = "9"
          sign = "yes"
          integers = "9"
          decimals = "0"
          middle_name = "fechaInicio"
        />

        <field
          java_name = "fec_fin"
          type = "int"
          size = "9"
          sign = "yes"
          integers = "9"
          decimals = "0"
          middle_name = "fechaFin"
        />

  </input>

  <output>

        <field
          java_name = "resultado"
          type = "int"
          size = "9"
          sign = "yes"
          integers = "9"
          decimals = "0"
          middle_name = "resultado"
        />

  </output>

</service>
